detect_advisor/__init__.py
detect_advisor/config.py
detect_advisor/global_values.py
detect_advisor/main.py
detect_advisor/messages.py
detect_advisor/output.py
detect_advisor/process.py
detect_advisor-1.0.10.dist-info/LICENSE
detect_advisor-1.0.10.dist-info/METADATA
detect_advisor-1.0.10.dist-info/WHEEL
detect_advisor-1.0.10.dist-info/entry_points.txt
detect_advisor-1.0.10.dist-info/top_level.txt
detect_advisor-1.0.10.dist-info/RECORD
