Metadata-Version: 2.2
Name: detect_advisor
Version: 1.0.10
Summary: Detect Advisor - prescan project folders to determine how to scan with Detect
Author-email: Matthew Brady <mbrad@blackduck.com>
Project-URL: Homepage, https://github.com/blackducksoftware/detect_advisor
Project-URL: Issues, https://github.com/blackducksoftware/detect_advisor/issues
Classifier: Programming Language :: Python :: 3
Classifier: License :: OSI Approved :: MIT License
Classifier: Operating System :: OS Independent
Requires-Python: >=3.8
License-File: LICENSE
